README.rst
setup.py
Python_OOXML.egg-info/PKG-INFO
Python_OOXML.egg-info/SOURCES.txt
Python_OOXML.egg-info/dependency_links.txt
Python_OOXML.egg-info/requires.txt
Python_OOXML.egg-info/top_level.txt
ooxml/__init__.py
ooxml/doc.py
ooxml/docxfile.py
ooxml/importer.py
ooxml/parse.py
ooxml/serialize.py