Metadata-Version: 1.1
Name: Python-OOXML
Version: 0.12
Summary: Python-OOXML is a Python library for parsing Office Open XML files.
Home-page: https://github.com/booktype/python-ooxml
Author: Aleksandar Erkalovic
Author-email: aerkalov@gmail.com
License: GNU Affero General Public License
Keywords: ooxml,docx
Platform: UNKNOWN
Classifier: Development Status :: 4 - Beta
Classifier: Intended Audience :: Developers
Classifier: Operating System :: OS Independent
Classifier: Programming Language :: Python :: 2.7
Classifier: Topic :: Software Development :: Libraries :: Python Modules
